{
    "/js/app.js": "/js/app.js",
    "/css/app.css": "/css/app.css",
    "/js/app.0be9d47e872771a0e5b7.hot-update.js": "/js/app.0be9d47e872771a0e5b7.hot-update.js",
    "/js/app.5abacefdcd74987597c5.hot-update.js": "/js/app.5abacefdcd74987597c5.hot-update.js",
    "/js/app.ddcd2abb75913e455a8b.hot-update.js": "/js/app.ddcd2abb75913e455a8b.hot-update.js",
    "/js/app.6f80efb577975672e19f.hot-update.js": "/js/app.6f80efb577975672e19f.hot-update.js",
    "/js/app.ae883bcb347aab27dfbf.hot-update.js": "/js/app.ae883bcb347aab27dfbf.hot-update.js",
    "/js/app.0731b08fcbddc9d6f4e7.hot-update.js": "/js/app.0731b08fcbddc9d6f4e7.hot-update.js",
    "/js/app.58e46c2a4f5e044ea36a.hot-update.js": "/js/app.58e46c2a4f5e044ea36a.hot-update.js",
    "/js/app.a0d4adb2ed4523e23e7e.hot-update.js": "/js/app.a0d4adb2ed4523e23e7e.hot-update.js",
    "/js/app.877ac94bc9545fe7c510.hot-update.js": "/js/app.877ac94bc9545fe7c510.hot-update.js",
    "/js/app.4d430e38c09a86678aff.hot-update.js": "/js/app.4d430e38c09a86678aff.hot-update.js",
    "/js/app.c942a980f5de9a257de9.hot-update.js": "/js/app.c942a980f5de9a257de9.hot-update.js",
    "/js/app.610712e4d2d66b0bba2c.hot-update.js": "/js/app.610712e4d2d66b0bba2c.hot-update.js",
    "/js/app.3dae140cbab8305113c7.hot-update.js": "/js/app.3dae140cbab8305113c7.hot-update.js",
    "/js/app.e7f5005150a365363fc4.hot-update.js": "/js/app.e7f5005150a365363fc4.hot-update.js",
    "/js/app.84a91106aad4c8ad9e00.hot-update.js": "/js/app.84a91106aad4c8ad9e00.hot-update.js",
    "/js/app.21d46b53bb50ccaa4077.hot-update.js": "/js/app.21d46b53bb50ccaa4077.hot-update.js",
    "/js/app.0aa27c926b7a269edb29.hot-update.js": "/js/app.0aa27c926b7a269edb29.hot-update.js",
    "/js/app.ccc9ad4149a94a5c482c.hot-update.js": "/js/app.ccc9ad4149a94a5c482c.hot-update.js",
    "/js/app.b3fd47a9390cab94b573.hot-update.js": "/js/app.b3fd47a9390cab94b573.hot-update.js",
    "/js/app.a900b83ca908585e2ce7.hot-update.js": "/js/app.a900b83ca908585e2ce7.hot-update.js",
    "/js/app.c41bacf984d630fe693c.hot-update.js": "/js/app.c41bacf984d630fe693c.hot-update.js",
    "/js/app.e60cea3200b00f0089ae.hot-update.js": "/js/app.e60cea3200b00f0089ae.hot-update.js",
    "/js/app.326af6bf8b3a64350726.hot-update.js": "/js/app.326af6bf8b3a64350726.hot-update.js",
    "/js/app.ec3c4dbb6a2f47d1f833.hot-update.js": "/js/app.ec3c4dbb6a2f47d1f833.hot-update.js",
    "/js/app.b93a9ea42b73dc8eb6f8.hot-update.js": "/js/app.b93a9ea42b73dc8eb6f8.hot-update.js",
    "/js/app.74451d32716b02778e43.hot-update.js": "/js/app.74451d32716b02778e43.hot-update.js",
    "/js/app.376a59970b655896c8cd.hot-update.js": "/js/app.376a59970b655896c8cd.hot-update.js",
    "/js/app.cf512801233c03c7aa7a.hot-update.js": "/js/app.cf512801233c03c7aa7a.hot-update.js",
    "/js/app.9d6f68ee30a7d6c03db0.hot-update.js": "/js/app.9d6f68ee30a7d6c03db0.hot-update.js",
    "/js/app.829f0500070bf7533399.hot-update.js": "/js/app.829f0500070bf7533399.hot-update.js",
    "/js/app.37a216a68586dde781b0.hot-update.js": "/js/app.37a216a68586dde781b0.hot-update.js",
    "/js/app.fc14e105a5900cedd3df.hot-update.js": "/js/app.fc14e105a5900cedd3df.hot-update.js",
    "/js/app.08b3bd0bbda26f9eb091.hot-update.js": "/js/app.08b3bd0bbda26f9eb091.hot-update.js",
    "/js/app.5902ff29e8a68c5c8a1e.hot-update.js": "/js/app.5902ff29e8a68c5c8a1e.hot-update.js",
    "/js/app.d3af2d94acc1c8b12f83.hot-update.js": "/js/app.d3af2d94acc1c8b12f83.hot-update.js",
    "/js/app.731a5132dc4b4f9b5a27.hot-update.js": "/js/app.731a5132dc4b4f9b5a27.hot-update.js",
    "/js/app.51339e26bd77767d7af6.hot-update.js": "/js/app.51339e26bd77767d7af6.hot-update.js",
    "/js/app.edc31d5c46164686f843.hot-update.js": "/js/app.edc31d5c46164686f843.hot-update.js",
    "/js/app.8845bcb1b1f7129825b3.hot-update.js": "/js/app.8845bcb1b1f7129825b3.hot-update.js",
    "/js/app.00963123a89fce2c18c3.hot-update.js": "/js/app.00963123a89fce2c18c3.hot-update.js",
    "/js/app.3769e888b62d4f19bc4b.hot-update.js": "/js/app.3769e888b62d4f19bc4b.hot-update.js",
    "/js/app.e04f52fb52c307e1c7a0.hot-update.js": "/js/app.e04f52fb52c307e1c7a0.hot-update.js",
    "/js/app.bc2a6c9703bfaa001244.hot-update.js": "/js/app.bc2a6c9703bfaa001244.hot-update.js",
    "/js/app.3baf064559bd3e814d8d.hot-update.js": "/js/app.3baf064559bd3e814d8d.hot-update.js",
    "/js/app.e55d03b0af2c3d428bff.hot-update.js": "/js/app.e55d03b0af2c3d428bff.hot-update.js",
    "/js/app.72992393e86655acb7da.hot-update.js": "/js/app.72992393e86655acb7da.hot-update.js",
    "/js/app.4b16cf32c6de7a281d61.hot-update.js": "/js/app.4b16cf32c6de7a281d61.hot-update.js",
    "/js/app.d6166bd7b6a1556d45d7.hot-update.js": "/js/app.d6166bd7b6a1556d45d7.hot-update.js",
    "/js/app.555b5da1a17d28bf5196.hot-update.js": "/js/app.555b5da1a17d28bf5196.hot-update.js",
    "/js/app.088947453ca31daa4503.hot-update.js": "/js/app.088947453ca31daa4503.hot-update.js",
    "/js/app.57e7c5e5d545c2f1b63e.hot-update.js": "/js/app.57e7c5e5d545c2f1b63e.hot-update.js",
    "/js/app.f538a6c892a5eb7bd56f.hot-update.js": "/js/app.f538a6c892a5eb7bd56f.hot-update.js",
    "/js/app.04120f2caa30338f3621.hot-update.js": "/js/app.04120f2caa30338f3621.hot-update.js",
    "/js/app.762d5efa6df4d5f77da2.hot-update.js": "/js/app.762d5efa6df4d5f77da2.hot-update.js",
    "/js/app.8c89846679b6cb7b2b88.hot-update.js": "/js/app.8c89846679b6cb7b2b88.hot-update.js",
    "/js/app.495626fe4f26cf801771.hot-update.js": "/js/app.495626fe4f26cf801771.hot-update.js",
    "/js/app.56c0e0305f3e1d59a764.hot-update.js": "/js/app.56c0e0305f3e1d59a764.hot-update.js",
    "/js/app.c24b851d10b1bd705ed2.hot-update.js": "/js/app.c24b851d10b1bd705ed2.hot-update.js",
    "/js/app.0f661257109883f4545f.hot-update.js": "/js/app.0f661257109883f4545f.hot-update.js",
    "/js/app.f6c91afe942430260ceb.hot-update.js": "/js/app.f6c91afe942430260ceb.hot-update.js",
    "/js/app.abfe2c40b98f415eab66.hot-update.js": "/js/app.abfe2c40b98f415eab66.hot-update.js",
    "/js/app.896f8d717bde640924ad.hot-update.js": "/js/app.896f8d717bde640924ad.hot-update.js",
    "/js/app.fdb2147379ec2a7f8e38.hot-update.js": "/js/app.fdb2147379ec2a7f8e38.hot-update.js",
    "/js/app.8d0240008b09a456c473.hot-update.js": "/js/app.8d0240008b09a456c473.hot-update.js",
    "/js/app.eff6f8a8486c81e68f44.hot-update.js": "/js/app.eff6f8a8486c81e68f44.hot-update.js",
    "/js/app.ecad79089f31860a731b.hot-update.js": "/js/app.ecad79089f31860a731b.hot-update.js",
    "/js/app.049492830eec5ae00af9.hot-update.js": "/js/app.049492830eec5ae00af9.hot-update.js",
    "/js/app.3698fd23e06e7f68578f.hot-update.js": "/js/app.3698fd23e06e7f68578f.hot-update.js",
    "/js/app.e30f698afcbfa94fd326.hot-update.js": "/js/app.e30f698afcbfa94fd326.hot-update.js",
    "/js/app.6c207c365d7f8980a097.hot-update.js": "/js/app.6c207c365d7f8980a097.hot-update.js",
    "/js/app.23b1da581f29dcd9d5f1.hot-update.js": "/js/app.23b1da581f29dcd9d5f1.hot-update.js",
    "/js/app.a1d8032a09910873dee6.hot-update.js": "/js/app.a1d8032a09910873dee6.hot-update.js",
    "/js/app.7a5328f3a924ec800500.hot-update.js": "/js/app.7a5328f3a924ec800500.hot-update.js",
    "/js/app.8115b669769b34907c15.hot-update.js": "/js/app.8115b669769b34907c15.hot-update.js",
    "/js/app.6c294f99f98ffe135de1.hot-update.js": "/js/app.6c294f99f98ffe135de1.hot-update.js",
    "/js/app.6ef58a99ef3df72b7694.hot-update.js": "/js/app.6ef58a99ef3df72b7694.hot-update.js",
    "/js/app.d0874fce70989728ab83.hot-update.js": "/js/app.d0874fce70989728ab83.hot-update.js",
    "/js/app.dcc82ab8534c23fbc42d.hot-update.js": "/js/app.dcc82ab8534c23fbc42d.hot-update.js",
    "/js/app.528a7d6f070432d260bb.hot-update.js": "/js/app.528a7d6f070432d260bb.hot-update.js",
    "/js/app.d84c6da3e05944be31af.hot-update.js": "/js/app.d84c6da3e05944be31af.hot-update.js",
    "/js/app.33a4158bd4e11859b4ff.hot-update.js": "/js/app.33a4158bd4e11859b4ff.hot-update.js",
    "/js/app.962e9edf77ae4bc80475.hot-update.js": "/js/app.962e9edf77ae4bc80475.hot-update.js",
    "/js/app.be24558ebbcdc5ddae54.hot-update.js": "/js/app.be24558ebbcdc5ddae54.hot-update.js",
    "/js/app.dad0257d2ca53470789e.hot-update.js": "/js/app.dad0257d2ca53470789e.hot-update.js",
    "/js/app.be2045fbd747284a479a.hot-update.js": "/js/app.be2045fbd747284a479a.hot-update.js",
    "/js/app.23978e4f523fc344af12.hot-update.js": "/js/app.23978e4f523fc344af12.hot-update.js",
    "/js/app.af5ae0e1a823a5859e97.hot-update.js": "/js/app.af5ae0e1a823a5859e97.hot-update.js",
    "/js/app.03105b76866dc43bab42.hot-update.js": "/js/app.03105b76866dc43bab42.hot-update.js",
    "/js/app.6f573bc655c7f2766d3b.hot-update.js": "/js/app.6f573bc655c7f2766d3b.hot-update.js",
    "/js/app.312b14206305d9afabf3.hot-update.js": "/js/app.312b14206305d9afabf3.hot-update.js",
    "/js/app.f4fefa7872cca7c01bdb.hot-update.js": "/js/app.f4fefa7872cca7c01bdb.hot-update.js",
    "/js/app.3b38dbc3c7f88bbc1d9a.hot-update.js": "/js/app.3b38dbc3c7f88bbc1d9a.hot-update.js",
    "/js/app.e0f7082c02fb72d768df.hot-update.js": "/js/app.e0f7082c02fb72d768df.hot-update.js",
    "/js/app.ec1d4735ba2a08770735.hot-update.js": "/js/app.ec1d4735ba2a08770735.hot-update.js",
    "/js/app.0b03787a8d135dd9a93f.hot-update.js": "/js/app.0b03787a8d135dd9a93f.hot-update.js",
    "/js/app.be00e5a7762805bf01f0.hot-update.js": "/js/app.be00e5a7762805bf01f0.hot-update.js",
    "/js/app.1233815f59eecbcf2179.hot-update.js": "/js/app.1233815f59eecbcf2179.hot-update.js",
    "/js/app.762fddfacfaed7ec8cb8.hot-update.js": "/js/app.762fddfacfaed7ec8cb8.hot-update.js",
    "/js/app.1faee7e1ad2b45283bbc.hot-update.js": "/js/app.1faee7e1ad2b45283bbc.hot-update.js",
    "/js/app.82e4f0f8702403070b8d.hot-update.js": "/js/app.82e4f0f8702403070b8d.hot-update.js",
    "/js/app.78544936a2cdddd9486a.hot-update.js": "/js/app.78544936a2cdddd9486a.hot-update.js",
    "/js/app.8b1f61f570b51378d41b.hot-update.js": "/js/app.8b1f61f570b51378d41b.hot-update.js",
    "/js/app.a4e0238e7d172b34755d.hot-update.js": "/js/app.a4e0238e7d172b34755d.hot-update.js",
    "/js/app.adab2c6b23c70cf74205.hot-update.js": "/js/app.adab2c6b23c70cf74205.hot-update.js",
    "/js/app.0506a08af04da98a80c6.hot-update.js": "/js/app.0506a08af04da98a80c6.hot-update.js",
    "/js/app.844909e95598c7ec1f35.hot-update.js": "/js/app.844909e95598c7ec1f35.hot-update.js",
    "/js/app.eabc0705e3bbbc0b853a.hot-update.js": "/js/app.eabc0705e3bbbc0b853a.hot-update.js",
    "/js/app.7913e8ec31903f7eff97.hot-update.js": "/js/app.7913e8ec31903f7eff97.hot-update.js",
    "/js/app.3815b5578df31051afd5.hot-update.js": "/js/app.3815b5578df31051afd5.hot-update.js",
    "/js/app.42c9f5c61ba55f2bbc77.hot-update.js": "/js/app.42c9f5c61ba55f2bbc77.hot-update.js",
    "/js/app.2c91903cffe0c767015d.hot-update.js": "/js/app.2c91903cffe0c767015d.hot-update.js",
    "/js/app.6df2b82b1b9447bbc767.hot-update.js": "/js/app.6df2b82b1b9447bbc767.hot-update.js",
    "/js/app.98da1bf456383d1b59ff.hot-update.js": "/js/app.98da1bf456383d1b59ff.hot-update.js",
    "/js/app.158ef6c377541514771c.hot-update.js": "/js/app.158ef6c377541514771c.hot-update.js",
    "/js/app.e9740650c48fc29e50b9.hot-update.js": "/js/app.e9740650c48fc29e50b9.hot-update.js",
    "/js/app.076452d00cf70df40919.hot-update.js": "/js/app.076452d00cf70df40919.hot-update.js",
    "/js/app.f0fe3922be102ae4a12c.hot-update.js": "/js/app.f0fe3922be102ae4a12c.hot-update.js",
    "/js/app.df8485ebf5a620982a7a.hot-update.js": "/js/app.df8485ebf5a620982a7a.hot-update.js",
    "/js/app.6ad93ba5611ca9f4cae1.hot-update.js": "/js/app.6ad93ba5611ca9f4cae1.hot-update.js",
    "/js/app.bc831b50c3aeb1168ec4.hot-update.js": "/js/app.bc831b50c3aeb1168ec4.hot-update.js",
    "/js/app.693e5c1f8da9edf133e9.hot-update.js": "/js/app.693e5c1f8da9edf133e9.hot-update.js",
    "/js/app.625817fdd412042a87f5.hot-update.js": "/js/app.625817fdd412042a87f5.hot-update.js",
    "/js/app.3bd3509aa442d7c7649e.hot-update.js": "/js/app.3bd3509aa442d7c7649e.hot-update.js",
    "/js/app.bce3d8b78ff20e48bf5d.hot-update.js": "/js/app.bce3d8b78ff20e48bf5d.hot-update.js",
    "/js/app.bdfa7c8bf3df55844d89.hot-update.js": "/js/app.bdfa7c8bf3df55844d89.hot-update.js",
    "/js/app.91351525d6747c8a234d.hot-update.js": "/js/app.91351525d6747c8a234d.hot-update.js",
    "/js/app.7d3795204fc78afd5aeb.hot-update.js": "/js/app.7d3795204fc78afd5aeb.hot-update.js",
    "/js/app.33b1cdfb50b97b1e1360.hot-update.js": "/js/app.33b1cdfb50b97b1e1360.hot-update.js",
    "/js/app.f112bef1fe518bdebb26.hot-update.js": "/js/app.f112bef1fe518bdebb26.hot-update.js",
    "/js/app.8228ecd3eedaf2b17137.hot-update.js": "/js/app.8228ecd3eedaf2b17137.hot-update.js",
    "/js/app.941420a0b3fcbdfae82c.hot-update.js": "/js/app.941420a0b3fcbdfae82c.hot-update.js",
    "/js/app.17a6a6e612047c384981.hot-update.js": "/js/app.17a6a6e612047c384981.hot-update.js",
    "/js/app.5635c18005097c4d4509.hot-update.js": "/js/app.5635c18005097c4d4509.hot-update.js",
    "/js/app.75ead45087e6197b9dee.hot-update.js": "/js/app.75ead45087e6197b9dee.hot-update.js",
    "/js/app.ad05dcb0b66d6e5fd5ed.hot-update.js": "/js/app.ad05dcb0b66d6e5fd5ed.hot-update.js",
    "/js/app.5628b0e53e8acb5582ac.hot-update.js": "/js/app.5628b0e53e8acb5582ac.hot-update.js",
    "/js/app.bc9f0a019a874e9d3ef6.hot-update.js": "/js/app.bc9f0a019a874e9d3ef6.hot-update.js",
    "/js/app.40eef4d330a136da0b3f.hot-update.js": "/js/app.40eef4d330a136da0b3f.hot-update.js",
    "/js/app.ec6ecc14beedab9d032a.hot-update.js": "/js/app.ec6ecc14beedab9d032a.hot-update.js",
    "/js/app.563bb88859110d72a541.hot-update.js": "/js/app.563bb88859110d72a541.hot-update.js",
    "/js/app.2c10841e8f967aa94f38.hot-update.js": "/js/app.2c10841e8f967aa94f38.hot-update.js",
    "/js/app.6f1ec1d66f86f52f675b.hot-update.js": "/js/app.6f1ec1d66f86f52f675b.hot-update.js",
    "/js/app.bde93e0abdbe2811febd.hot-update.js": "/js/app.bde93e0abdbe2811febd.hot-update.js",
    "/js/app.0f2d0ff2fb887de596d6.hot-update.js": "/js/app.0f2d0ff2fb887de596d6.hot-update.js",
    "/js/app.be8529ab1367640e4916.hot-update.js": "/js/app.be8529ab1367640e4916.hot-update.js",
    "/js/app.2bd52977c5c67e5abeab.hot-update.js": "/js/app.2bd52977c5c67e5abeab.hot-update.js",
    "/js/app.bb00bd6557ba0f9224fe.hot-update.js": "/js/app.bb00bd6557ba0f9224fe.hot-update.js",
    "/js/app.94acf78187b8d90152b0.hot-update.js": "/js/app.94acf78187b8d90152b0.hot-update.js",
    "/js/app.06d7e74f409a9b8a1d93.hot-update.js": "/js/app.06d7e74f409a9b8a1d93.hot-update.js",
    "/js/app.a9ed6afa80f8d36dbeee.hot-update.js": "/js/app.a9ed6afa80f8d36dbeee.hot-update.js",
    "/js/app.dbd1d2e4744b553c8268.hot-update.js": "/js/app.dbd1d2e4744b553c8268.hot-update.js",
    "/js/app.c0bda49dd89f208efeb3.hot-update.js": "/js/app.c0bda49dd89f208efeb3.hot-update.js",
    "/js/app.5efe92c331b1060b171f.hot-update.js": "/js/app.5efe92c331b1060b171f.hot-update.js",
    "/js/app.c56fff16b5863fee2f2d.hot-update.js": "/js/app.c56fff16b5863fee2f2d.hot-update.js",
    "/js/app.ba9a55e626650a413484.hot-update.js": "/js/app.ba9a55e626650a413484.hot-update.js",
    "/js/app.74e1e7f69538cf734478.hot-update.js": "/js/app.74e1e7f69538cf734478.hot-update.js",
    "/js/app.58e339b67f43beb3b84f.hot-update.js": "/js/app.58e339b67f43beb3b84f.hot-update.js",
    "/js/app.5453edc98239a3d2d159.hot-update.js": "/js/app.5453edc98239a3d2d159.hot-update.js",
    "/js/app.6d86db9bfa434887424f.hot-update.js": "/js/app.6d86db9bfa434887424f.hot-update.js",
    "/js/app.247fe1c96eb03719d97a.hot-update.js": "/js/app.247fe1c96eb03719d97a.hot-update.js",
    "/js/app.1cc66b23e64519f9ca5b.hot-update.js": "/js/app.1cc66b23e64519f9ca5b.hot-update.js",
    "/js/app.5e653c0bb19b5aa1b953.hot-update.js": "/js/app.5e653c0bb19b5aa1b953.hot-update.js",
    "/js/app.60b1347476122b4e3fa1.hot-update.js": "/js/app.60b1347476122b4e3fa1.hot-update.js",
    "/js/app.0d991b0037207c9018c6.hot-update.js": "/js/app.0d991b0037207c9018c6.hot-update.js",
    "/js/app.8cc6762ad65844960f09.hot-update.js": "/js/app.8cc6762ad65844960f09.hot-update.js",
    "/js/app.bd45955c8bd7cd8c92dd.hot-update.js": "/js/app.bd45955c8bd7cd8c92dd.hot-update.js",
    "/js/app.9dce5c878306c420a227.hot-update.js": "/js/app.9dce5c878306c420a227.hot-update.js",
    "/js/app.44560f449bebc7098eaf.hot-update.js": "/js/app.44560f449bebc7098eaf.hot-update.js",
    "/js/app.132e53954b3e0c9f3bd5.hot-update.js": "/js/app.132e53954b3e0c9f3bd5.hot-update.js",
    "/js/app.f4b34b804be26b0df835.hot-update.js": "/js/app.f4b34b804be26b0df835.hot-update.js",
    "/js/app.2c2a77cb964b08bc3232.hot-update.js": "/js/app.2c2a77cb964b08bc3232.hot-update.js",
    "/js/app.509e432b6299b5164150.hot-update.js": "/js/app.509e432b6299b5164150.hot-update.js",
    "/js/app.6ccd49c8baeaa32f52ee.hot-update.js": "/js/app.6ccd49c8baeaa32f52ee.hot-update.js",
    "/js/app.ad5e23c5a3fabad685ef.hot-update.js": "/js/app.ad5e23c5a3fabad685ef.hot-update.js",
    "/js/app.2a02db33cce0f981e081.hot-update.js": "/js/app.2a02db33cce0f981e081.hot-update.js",
    "/js/app.4a6e4eec6c5d75ccc256.hot-update.js": "/js/app.4a6e4eec6c5d75ccc256.hot-update.js",
    "/js/app.e99d0f0bd236085d5370.hot-update.js": "/js/app.e99d0f0bd236085d5370.hot-update.js",
    "/js/app.02b6a5f3f6aa13eb0453.hot-update.js": "/js/app.02b6a5f3f6aa13eb0453.hot-update.js",
    "/js/app.4cc2090f2f08d961d437.hot-update.js": "/js/app.4cc2090f2f08d961d437.hot-update.js",
    "/js/app.4fbbdf05263508d8fee9.hot-update.js": "/js/app.4fbbdf05263508d8fee9.hot-update.js",
    "/js/app.7ad7f512cba166af2ca2.hot-update.js": "/js/app.7ad7f512cba166af2ca2.hot-update.js",
    "/js/app.258b021a2c0123bab746.hot-update.js": "/js/app.258b021a2c0123bab746.hot-update.js",
    "/js/app.ac0d5a638519ae557c8a.hot-update.js": "/js/app.ac0d5a638519ae557c8a.hot-update.js",
    "/js/app.173f7d4fa0974f0a5ccf.hot-update.js": "/js/app.173f7d4fa0974f0a5ccf.hot-update.js",
    "/js/app.fdc2bc57b9c5d1e1eace.hot-update.js": "/js/app.fdc2bc57b9c5d1e1eace.hot-update.js",
    "/js/app.55b08fcd890b332cebf1.hot-update.js": "/js/app.55b08fcd890b332cebf1.hot-update.js",
    "/js/app.8553396845e4bb262ee5.hot-update.js": "/js/app.8553396845e4bb262ee5.hot-update.js",
    "/js/app.c8517b46d64b28029836.hot-update.js": "/js/app.c8517b46d64b28029836.hot-update.js"
}
