{
    "/js/app.js": "/js/app.js",
    "/css/app.css": "/css/app.css",
    "/js/app.44dc13b11a3dca577100.hot-update.js": "/js/app.44dc13b11a3dca577100.hot-update.js",
    "/js/app.ae9d95efc65571d3fccd.hot-update.js": "/js/app.ae9d95efc65571d3fccd.hot-update.js",
    "/js/app.62f4ef5ce91c0d979fee.hot-update.js": "/js/app.62f4ef5ce91c0d979fee.hot-update.js",
    "/js/app.2ae4eac6fdc2165fb84f.hot-update.js": "/js/app.2ae4eac6fdc2165fb84f.hot-update.js",
    "/js/app.3912f1bbec2593a9f74f.hot-update.js": "/js/app.3912f1bbec2593a9f74f.hot-update.js",
    "/js/app.0b1019d187a95154a221.hot-update.js": "/js/app.0b1019d187a95154a221.hot-update.js",
    "/js/app.002cc397e0d068cd40e5.hot-update.js": "/js/app.002cc397e0d068cd40e5.hot-update.js",
    "/js/app.330ee2182dc33359556a.hot-update.js": "/js/app.330ee2182dc33359556a.hot-update.js",
    "/js/app.11bbdd3700b4c5b3b3c5.hot-update.js": "/js/app.11bbdd3700b4c5b3b3c5.hot-update.js",
    "/js/app.04f8b3a44dbe4f5f64b5.hot-update.js": "/js/app.04f8b3a44dbe4f5f64b5.hot-update.js",
    "/js/app.7fbda688b79de0e6ead4.hot-update.js": "/js/app.7fbda688b79de0e6ead4.hot-update.js",
    "/js/app.611f4a219278be4e0468.hot-update.js": "/js/app.611f4a219278be4e0468.hot-update.js",
    "/js/app.d78b8dd15dd273d19d48.hot-update.js": "/js/app.d78b8dd15dd273d19d48.hot-update.js",
    "/js/app.7e89f5813ffcae382383.hot-update.js": "/js/app.7e89f5813ffcae382383.hot-update.js",
    "/js/app.5b189f28654d1d885c10.hot-update.js": "/js/app.5b189f28654d1d885c10.hot-update.js",
    "/js/app.b44cd3ab6e28f26a3e48.hot-update.js": "/js/app.b44cd3ab6e28f26a3e48.hot-update.js",
    "/js/app.42ee5ebd0cffa2e3ab64.hot-update.js": "/js/app.42ee5ebd0cffa2e3ab64.hot-update.js",
    "/js/app.c744726af457ccef766b.hot-update.js": "/js/app.c744726af457ccef766b.hot-update.js",
    "/js/app.9cfb7cd066a73a23368e.hot-update.js": "/js/app.9cfb7cd066a73a23368e.hot-update.js",
    "/js/app.2c732e60598fae654ce1.hot-update.js": "/js/app.2c732e60598fae654ce1.hot-update.js",
    "/js/app.0d751ccb29b0dd440c04.hot-update.js": "/js/app.0d751ccb29b0dd440c04.hot-update.js",
    "/js/app.2a5bb9c60a8751d1c47d.hot-update.js": "/js/app.2a5bb9c60a8751d1c47d.hot-update.js",
    "/js/app.fe703290bf67ec1f985d.hot-update.js": "/js/app.fe703290bf67ec1f985d.hot-update.js",
    "/js/app.e706d4ba36fbb09f1c6f.hot-update.js": "/js/app.e706d4ba36fbb09f1c6f.hot-update.js",
    "/js/app.d626d8ec54703a03313e.hot-update.js": "/js/app.d626d8ec54703a03313e.hot-update.js",
    "/js/app.56ac72f51f0d39e162db.hot-update.js": "/js/app.56ac72f51f0d39e162db.hot-update.js",
    "/js/app.a24d54a2a94733dcf513.hot-update.js": "/js/app.a24d54a2a94733dcf513.hot-update.js",
    "/js/app.cdb37811273511bb6ee6.hot-update.js": "/js/app.cdb37811273511bb6ee6.hot-update.js",
    "/js/app.d4900cc09e6bc50df79e.hot-update.js": "/js/app.d4900cc09e6bc50df79e.hot-update.js",
    "/js/app.07bb2cd59a50795a709a.hot-update.js": "/js/app.07bb2cd59a50795a709a.hot-update.js",
    "/js/app.5c54a46d54082d65b65a.hot-update.js": "/js/app.5c54a46d54082d65b65a.hot-update.js",
    "/js/app.4c3f8d849f5215038fdf.hot-update.js": "/js/app.4c3f8d849f5215038fdf.hot-update.js",
    "/js/app.65cad8afa4b36c94ff46.hot-update.js": "/js/app.65cad8afa4b36c94ff46.hot-update.js",
    "/js/app.11df9398fe2dffcb984f.hot-update.js": "/js/app.11df9398fe2dffcb984f.hot-update.js",
    "/js/app.49ddda81fb485a891742.hot-update.js": "/js/app.49ddda81fb485a891742.hot-update.js",
    "/js/app.09ac407d1e55045f24c4.hot-update.js": "/js/app.09ac407d1e55045f24c4.hot-update.js",
    "/js/app.bf5a2d0b568ef7620a84.hot-update.js": "/js/app.bf5a2d0b568ef7620a84.hot-update.js",
    "/js/app.a7f0ab8f36f03fea1299.hot-update.js": "/js/app.a7f0ab8f36f03fea1299.hot-update.js",
    "/js/app.ba5298a2ae5053598405.hot-update.js": "/js/app.ba5298a2ae5053598405.hot-update.js",
    "/js/app.4b157135031346c7df81.hot-update.js": "/js/app.4b157135031346c7df81.hot-update.js",
    "/js/app.70658b8e31eb1f8b2ac9.hot-update.js": "/js/app.70658b8e31eb1f8b2ac9.hot-update.js",
    "/js/app.6ee0c2b054121cbe70f0.hot-update.js": "/js/app.6ee0c2b054121cbe70f0.hot-update.js",
    "/js/app.485e9ae58095355b1c4e.hot-update.js": "/js/app.485e9ae58095355b1c4e.hot-update.js",
    "/js/app.9b660a773cfeee2c5cc7.hot-update.js": "/js/app.9b660a773cfeee2c5cc7.hot-update.js",
    "/js/app.5d54b49a653675e620c2.hot-update.js": "/js/app.5d54b49a653675e620c2.hot-update.js",
    "/js/app.2f4921decf31a67b8f50.hot-update.js": "/js/app.2f4921decf31a67b8f50.hot-update.js",
    "/js/app.3fcb94e44efc2680b404.hot-update.js": "/js/app.3fcb94e44efc2680b404.hot-update.js",
    "/js/app.447ac2e56bd448b5283f.hot-update.js": "/js/app.447ac2e56bd448b5283f.hot-update.js",
    "/js/app.0b25336b2930848496ba.hot-update.js": "/js/app.0b25336b2930848496ba.hot-update.js",
    "/js/app.9144202c1d1af89f8982.hot-update.js": "/js/app.9144202c1d1af89f8982.hot-update.js",
    "/js/app.837cd46030958b9c5225.hot-update.js": "/js/app.837cd46030958b9c5225.hot-update.js",
    "/js/app.0c9219a93f4bfe348572.hot-update.js": "/js/app.0c9219a93f4bfe348572.hot-update.js",
    "/js/app.0126fc9690ee189b0472.hot-update.js": "/js/app.0126fc9690ee189b0472.hot-update.js",
    "/js/app.d79e0ec56646e2265bfc.hot-update.js": "/js/app.d79e0ec56646e2265bfc.hot-update.js",
    "/js/app.bf83e9b62bbb82258694.hot-update.js": "/js/app.bf83e9b62bbb82258694.hot-update.js",
    "/js/app.d6d31d39c82d737b9084.hot-update.js": "/js/app.d6d31d39c82d737b9084.hot-update.js",
    "/js/app.beaf949621db4bdc301a.hot-update.js": "/js/app.beaf949621db4bdc301a.hot-update.js",
    "/js/app.58b7046ebbc4e38b6c58.hot-update.js": "/js/app.58b7046ebbc4e38b6c58.hot-update.js",
    "/js/app.31d2129b352947f082cb.hot-update.js": "/js/app.31d2129b352947f082cb.hot-update.js",
    "/js/app.5c92aca2a973d9920939.hot-update.js": "/js/app.5c92aca2a973d9920939.hot-update.js",
    "/js/app.78ef75dc9e50aa7606b9.hot-update.js": "/js/app.78ef75dc9e50aa7606b9.hot-update.js",
    "/js/app.ed71efe5acf73a82af81.hot-update.js": "/js/app.ed71efe5acf73a82af81.hot-update.js"
}
